webinardump/__init__.py
webinardump/cli.py
webinardump/utils.py
webinardump/dumpers/__init__.py
webinardump/dumpers/base.py
webinardump/dumpers/webinarru.py
webinardump/dumpers/yadisk.py
webinardump-0.1.1.dist-info/METADATA
webinardump-0.1.1.dist-info/WHEEL
webinardump-0.1.1.dist-info/entry_points.txt
webinardump-0.1.1.dist-info/RECORD
