Metadata-Version: 2.4
Name: webinardump
Version: 0.1.1
Summary: Make local backup copies of webinars
Project-URL: Homepage, https://github.com/idlesign/webinardump
Author-email: Igor Starikov <idlesign@yandex.ru>
License-Expression: BSD-3-Clause
Keywords: backup,webinars
Requires-Python: >=3.11
Requires-Dist: requests>=2.31.0
